ssh_tarpit/__init__.py
ssh_tarpit/__main__.py
ssh_tarpit/constants.py
ssh_tarpit/log2csv.py
ssh_tarpit/server.py
ssh_tarpit/utils.py
ssh_tarpit-0.4.2.dist-info/LICENSE
ssh_tarpit-0.4.2.dist-info/METADATA
ssh_tarpit-0.4.2.dist-info/WHEEL
ssh_tarpit-0.4.2.dist-info/entry_points.txt
ssh_tarpit-0.4.2.dist-info/top_level.txt
ssh_tarpit-0.4.2.dist-info/zip-safe
ssh_tarpit-0.4.2.dist-info/RECORD
