Metadata-Version: 2.1
Name: ssh_tarpit
Version: 0.4.2
Summary: SSH tarpit that slowly sends an endless banner
Home-page: https://github.com/Snawoot/ssh-tarpit
Author: Vladislav Yarmak
Author-email: vladislav-ex-src@vm-0.com
License: MIT
Classifier: Programming Language :: Python :: 3.5
Classifier: Programming Language :: Python :: 3.6
Classifier: Programming Language :: Python :: 3.7
Classifier: Operating System :: OS Independent
Classifier: Development Status :: 4 - Beta
Classifier: Environment :: Console
Classifier: Environment :: No Input/Output (Daemon)
Classifier: Intended Audience :: System Administrators
Classifier: Natural Language :: English
Classifier: Topic :: Internet
Classifier: Topic :: Utilities
Classifier: Topic :: Security
Requires-Python: >=3.5.3
License-File: LICENSE
